django_nutrition/__init__.py
django_nutrition/admin.py
django_nutrition/api.py
django_nutrition/apps.py
django_nutrition/models.py
django_nutrition/tests.py
django_nutrition/urls.py
django_nutrition/views.py
django_nutrition/static/nutrition/css/base.css
django_nutrition/static/nutrition/css/styles.css
django_nutrition/templates/django_nutrition/add_portion.html
django_nutrition/templates/django_nutrition/base-form.html
django_nutrition/templates/django_nutrition/base-simple.html
django_nutrition/templates/django_nutrition/base.html
django_nutrition/templates/django_nutrition/day.html
django_nutrition/templates/django_nutrition/days-calendar.html
django_nutrition/templates/django_nutrition/days-table.html
django_nutrition/templates/django_nutrition/days.html
django_nutrition/templates/django_nutrition/food_form.html
django_nutrition/templates/django_nutrition/foods.html
django_nutrition/templates/django_nutrition/header.html
django_nutrition/templates/django_nutrition/login.html
django_nutrition/templates/django_nutrition/meals.html
django_nutrition/templates/django_nutrition/portion_confirm_delete.html
django_nutrition/templates/django_nutrition/portions.html
django_nutrition/templates/django_nutrition/style-test.html
django_nutrition/templates/django_nutrition/user-preferences.html
django_nutrition/utils/__init__.py
django_nutrition/utils/context_processors.py
django_nutrition-0.5.0.dist-info/LICENSE.txt
django_nutrition-0.5.0.dist-info/METADATA
django_nutrition-0.5.0.dist-info/WHEEL
django_nutrition-0.5.0.dist-info/top_level.txt
django_nutrition-0.5.0.dist-info/RECORD
