Metadata-Version: 2.1
Name: django-nutrition
Version: 0.5.0
Summary: A Django app to track meals and calories.
Author-email: Erik Reid <noreply@no.domain>
Project-URL: Homepage, https://github.com/susrik/django-nutrition
Classifier: Environment :: Web Environment
Classifier: Framework :: Django
Classifier: Framework :: Django :: 5.1
Classifier: Intended Audience :: Developers
Classifier: License :: OSI Approved :: MIT License
Classifier: Operating System :: OS Independent
Classifier: Programming Language :: Python
Classifier: Programming Language :: Python :: 3
Classifier: Programming Language :: Python :: 3 :: Only
Classifier: Programming Language :: Python :: 3.10
Classifier: Programming Language :: Python :: 3.11
Classifier: Programming Language :: Python :: 3.12
Classifier: Topic :: Internet :: WWW/HTTP
Classifier: Topic :: Internet :: WWW/HTTP :: Dynamic Content
Classifier: Development Status :: 4 - Beta
Requires-Python: >=3.10
License-File: LICENSE.txt
Requires-Dist: django >=5.1
Requires-Dist: djangorestframework
